.source library/src/org/kiama/example/minijava/tests/bubblesort.java
.class public BubbleSort
.super java/lang/Object

.method <init>()V
.limit stack 1
.limit locals 1
    aload_0
    invokespecial java/lang/Object/<init>()V
    return
.end method

.method public static main([Ljava/lang/String;)V
.limit stack 3
.limit locals 2
    getstatic java/lang/System/out Ljava/io/PrintStream;
    new BBS
    dup
    invokespecial BBS/<init>()V
    bipush 10
    invokevirtual BBS/Start(I)I
    invokevirtual java/io/PrintStream/println(I)V
    return
.end method
.source library/src/org/kiama/example/minijava/tests/bubblesort.java
.class public BBS
.super java/lang/Object
.field public number [I
.field public size I

.method <init>()V
.limit stack 1
.limit locals 1
    aload_0
    invokespecial java/lang/Object/<init>()V
    return
.end method

.method public Start(I)I
.limit stack 2
.limit locals 3
    aload 0
    iload 1
    invokevirtual BBS/Init(I)I
    istore 2
    aload 0
    invokevirtual BBS/Print()I
    istore 2
    getstatic java/lang/System/out Ljava/io/PrintStream;
    ldc 99999
    invokevirtual java/io/PrintStream/println(I)V
    aload 0
    invokevirtual BBS/Sort()I
    istore 2
    aload 0
    invokevirtual BBS/Print()I
    istore 2
    iconst_0
    ireturn
.end method

.method public Sort()I
.limit stack 13
.limit locals 10
    aload 0
    getfield BBS/size I
    iconst_1
    isub
    istore 1
    iconst_0
    iconst_1
    isub
    istore 2
L1:
    iload 2
    iload 1
    if_icmpge L3
    iconst_1
    goto L4
L3:
    iconst_0
L4:
    ifeq L2
    iconst_1
    istore 3
L5:
    iload 3
    iload 1
    iconst_1
    iadd
    if_icmpge L7
    iconst_1
    goto L8
L7:
    iconst_0
L8:
    ifeq L6
    iload 3
    iconst_1
    isub
    istore 4
    aload 0
    getfield BBS/number [I
    iload 4
    iaload
    istore 5
    aload 0
    getfield BBS/number [I
    iload 3
    iaload
    istore 6
    iload 6
    iload 5
    if_icmpge L11
    iconst_1
    goto L12
L11:
    iconst_0
L12:
    ifeq L9
    iload 3
    iconst_1
    isub
    istore 7
    aload 0
    getfield BBS/number [I
    iload 7
    iaload
    istore 8
    aload 0
    getfield BBS/number [I
    iload 7
    aload 0
    getfield BBS/number [I
    iload 3
    iaload
    iastore
    aload 0
    getfield BBS/number [I
    iload 3
    iload 8
    iastore
    goto L10
L9:
    iconst_0
    istore 9
L10:
    iload 3
    iconst_1
    iadd
    istore 3
    goto L5
L6:
    iload 1
    iconst_1
    isub
    istore 1
    goto L1
L2:
    iconst_0
    ireturn
.end method

.method public Print()I
.limit stack 6
.limit locals 2
    iconst_0
    istore 1
L1:
    iload 1
    aload 0
    getfield BBS/size I
    if_icmpge L3
    iconst_1
    goto L4
L3:
    iconst_0
L4:
    ifeq L2
    getstatic java/lang/System/out Ljava/io/PrintStream;
    aload 0
    getfield BBS/number [I
    iload 1
    iaload
    invokevirtual java/io/PrintStream/println(I)V
    iload 1
    iconst_1
    iadd
    istore 1
    goto L1
L2:
    iconst_0
    ireturn
.end method

.method public Init(I)I
.limit stack 13
.limit locals 2
    aload 0
    iload 1
    putfield BBS/size I
    aload 0
    iload 1
    newarray int
    putfield BBS/number [I
    aload 0
    getfield BBS/number [I
    iconst_0
    bipush 20
    iastore
    aload 0
    getfield BBS/number [I
    iconst_1
    bipush 7
    iastore
    aload 0
    getfield BBS/number [I
    iconst_2
    bipush 12
    iastore
    aload 0
    getfield BBS/number [I
    iconst_3
    bipush 18
    iastore
    aload 0
    getfield BBS/number [I
    iconst_4
    iconst_2
    iastore
    aload 0
    getfield BBS/number [I
    iconst_5
    bipush 11
    iastore
    aload 0
    getfield BBS/number [I
    bipush 6
    bipush 6
    iastore
    aload 0
    getfield BBS/number [I
    bipush 7
    bipush 9
    iastore
    aload 0
    getfield BBS/number [I
    bipush 8
    bipush 19
    iastore
    aload 0
    getfield BBS/number [I
    bipush 9
    iconst_5
    iastore
    iconst_0
    ireturn
.end method
