.source src/org/kiama/example/minijava/tests/quicksort.java
.class public QuickSort
.super java/lang/Object

.method <init>()V
.limit stack 1
.limit locals 1
    aload_0
    invokespecial java/lang/Object/<init>()V
    return
.end method

.method public static main([Ljava/lang/String;)V
.limit stack 3
.limit locals 2
    getstatic java/lang/System/out Ljava/io/PrintStream;
    new QS
    dup
    invokespecial QS/<init>()V
    bipush 10
    invokevirtual QS/Start(I)I
    invokevirtual java/io/PrintStream/println(I)V
    return
.end method

.source src/org/kiama/example/minijava/tests/quicksort.java
.class public QS
.super java/lang/Object
.field public number [I
.field public size I

.method <init>()V
.limit stack 1
.limit locals 1
    aload_0
    invokespecial java/lang/Object/<init>()V
    return
.end method

.method public Start(I)I
.limit stack 4
.limit locals 3
    aload 0
    iload 1
    invokevirtual QS/Init(I)I
    istore 2
    aload 0
    invokevirtual QS/Print()I
    istore 2
    getstatic java/lang/System/out Ljava/io/PrintStream;
    ldc 9999
    invokevirtual java/io/PrintStream/println(I)V
    aload 0
    getfield QS/size I
    iconst_1
    isub
    istore 2
    aload 0
    iconst_0
    iload 2
    invokevirtual QS/Sort(II)I
    istore 2
    aload 0
    invokevirtual QS/Print()I
    istore 2
    iconst_0
    ireturn
.end method

.method public Sort(II)I
.limit stack 22
.limit locals 11
    iconst_0
    istore 3
    iload 1
    iload 2
    if_icmpge L3
    iconst_1
    goto L4
L3:
    iconst_0
L4:
    ifeq L1
    aload 0
    getfield QS/number [I
    iload 2
    iaload
    istore 4
    iload 1
    iconst_1
    isub
    istore 5
    iload 2
    istore 6
    iconst_1
    istore 7
L5:
    iload 7
    ifeq L6
    iconst_1
    istore 8
L7:
    iload 8
    ifeq L8
    iload 5
    iconst_1
    iadd
    istore 5
    aload 0
    getfield QS/number [I
    iload 5
    iaload
    istore 9
    iload 9
    iload 4
    if_icmpge L13
    iconst_1
    goto L14
L13:
    iconst_0
L14:
    ifeq L11
    iconst_0
    goto L12
L11:
    iconst_1
L12:
    ifeq L9
    iconst_0
    istore 8
    goto L10
L9:
    iconst_1
    istore 8
L10:
    goto L7
L8:
    iconst_1
    istore 8
L15:
    iload 8
    ifeq L16
    iload 6
    iconst_1
    isub
    istore 6
    aload 0
    getfield QS/number [I
    iload 6
    iaload
    istore 9
    iload 4
    iload 9
    if_icmpge L21
    iconst_1
    goto L22
L21:
    iconst_0
L22:
    ifeq L19
    iconst_0
    goto L20
L19:
    iconst_1
L20:
    ifeq L17
    iconst_0
    istore 8
    goto L18
L17:
    iconst_1
    istore 8
L18:
    goto L15
L16:
    aload 0
    getfield QS/number [I
    iload 5
    iaload
    istore 3
    aload 0
    getfield QS/number [I
    iload 5
    aload 0
    getfield QS/number [I
    iload 6
    iaload
    iastore
    aload 0
    getfield QS/number [I
    iload 6
    iload 3
    iastore
    iload 6
    iload 5
    iconst_1
    iadd
    if_icmpge L25
    iconst_1
    goto L26
L25:
    iconst_0
L26:
    ifeq L23
    iconst_0
    istore 7
    goto L24
L23:
    iconst_1
    istore 7
L24:
    goto L5
L6:
    aload 0
    getfield QS/number [I
    iload 6
    aload 0
    getfield QS/number [I
    iload 5
    iaload
    iastore
    aload 0
    getfield QS/number [I
    iload 5
    aload 0
    getfield QS/number [I
    iload 2
    iaload
    iastore
    aload 0
    getfield QS/number [I
    iload 2
    iload 3
    iastore
    aload 0
    iload 1
    iload 5
    iconst_1
    isub
    invokevirtual QS/Sort(II)I
    istore 10
    aload 0
    iload 5
    iconst_1
    iadd
    iload 2
    invokevirtual QS/Sort(II)I
    istore 10
    goto L2
L1:
    iconst_0
    istore 10
L2:
    iconst_0
    ireturn
.end method

.method public Print()I
.limit stack 6
.limit locals 2
    iconst_0
    istore 1
L1:
    iload 1
    aload 0
    getfield QS/size I
    if_icmpge L3
    iconst_1
    goto L4
L3:
    iconst_0
L4:
    ifeq L2
    getstatic java/lang/System/out Ljava/io/PrintStream;
    aload 0
    getfield QS/number [I
    iload 1
    iaload
    invokevirtual java/io/PrintStream/println(I)V
    iload 1
    iconst_1
    iadd
    istore 1
    goto L1
L2:
    iconst_0
    ireturn
.end method

.method public Init(I)I
.limit stack 13
.limit locals 2
    aload 0
    iload 1
    putfield QS/size I
    aload 0
    iload 1
    newarray int
    putfield QS/number [I
    aload 0
    getfield QS/number [I
    iconst_0
    bipush 20
    iastore
    aload 0
    getfield QS/number [I
    iconst_1
    bipush 7
    iastore
    aload 0
    getfield QS/number [I
    iconst_2
    bipush 12
    iastore
    aload 0
    getfield QS/number [I
    iconst_3
    bipush 18
    iastore
    aload 0
    getfield QS/number [I
    iconst_4
    iconst_2
    iastore
    aload 0
    getfield QS/number [I
    iconst_5
    bipush 11
    iastore
    aload 0
    getfield QS/number [I
    bipush 6
    bipush 6
    iastore
    aload 0
    getfield QS/number [I
    bipush 7
    bipush 9
    iastore
    aload 0
    getfield QS/number [I
    bipush 8
    bipush 19
    iastore
    aload 0
    getfield QS/number [I
    bipush 9
    iconst_5
    iastore
    iconst_0
    ireturn
.end method

