.source src/org/kiama/example/minijava/tests/whileone.java
.class public WhileOne
.super java/lang/Object

.method <init>()V
.limit stack 1
.limit locals 1
    aload_0
    invokespecial java/lang/Object/<init>()V
    return
.end method

.method public static main([Ljava/lang/String;)V
.limit stack 3
.limit locals 2
    getstatic java/lang/System/out Ljava/io/PrintStream;
    new WhileOneClass
    dup
    invokespecial WhileOneClass/<init>()V
    invokevirtual WhileOneClass/run()I
    invokevirtual java/io/PrintStream/println(I)V
    return
.end method

.source src/org/kiama/example/minijava/tests/whileone.java
.class public WhileOneClass
.super java/lang/Object

.method <init>()V
.limit stack 1
.limit locals 1
    aload_0
    invokespecial java/lang/Object/<init>()V
    return
.end method

.method public run()I
.limit stack 3
.limit locals 2
    iconst_0
    istore 1
L1:
    iload 1
    iconst_1
    if_icmpge L3
    iconst_1
    goto L4
L3:
    iconst_0
L4:
    ifeq L2
    iload 1
    iconst_1
    iadd
    istore 1
    goto L1
L2:
    iload 1
    ireturn
.end method

